{
  "main": {
    "id": "2ffe0a130d9f4d96",
    "type": "split",
    "children": [
      {
        "id": "89583f6c23698b41",
        "type": "tabs",
        "children": [
          {
            "id": "343b98d9e91f4cd8",
            "type": "leaf",
            "state": {
              "type": "markdown",
              "state": {
                "file": "docs/zh/dev/advanced-widget.md",
                "mode": "source",
                "source": false
              }
            }
          }
        ]
      }
    ],
    "direction": "vertical"
  },
  "left": {
    "id": "f4d98b55ca532e50",
    "type": "split",
    "children": [
      {
        "id": "0d62bd51f6210eec",
        "type": "tabs",
        "children": [
          {
            "id": "12f1a9a2fc022301",
            "type": "leaf",
            "state": {
              "type": "file-explorer",
              "state": {
                "sortOrder": "alphabetical"
              }
            }
          },
          {
            "id": "fedc862c773d3bd0",
            "type": "leaf",
            "state": {
              "type": "search",
              "state": {
                "query": "",
                "matchingCase": false,
                "explainSearch": false,
                "collapseAll": false,
                "extraContext": false,
                "sortOrder": "alphabetical"
              }
            }
          },
          {
            "id": "46cc7eafb0960650",
            "type": "leaf",
            "state": {
              "type": "bookmarks",
              "state": {}
            }
          }
        ]
      }
    ],
    "direction": "horizontal",
    "width": 300
  },
  "right": {
    "id": "90c0124cf12f82db",
    "type": "split",
    "children": [
      {
        "id": "687acd0359007946",
        "type": "tabs",
        "children": [
          {
            "id": "6aef8f422f0b4f75",
            "type": "leaf",
            "state": {
              "type": "backlink",
              "state": {
                "file": "docs/zh/dev/advanced-widget.md",
                "collapseAll": false,
                "extraContext": false,
                "sortOrder": "alphabetical",
                "showSearch": false,
                "searchQuery": "",
                "backlinkCollapsed": false,
                "unlinkedCollapsed": true
              }
            }
          },
          {
            "id": "1d8ff64e162f2725",
            "type": "leaf",
            "state": {
              "type": "outgoing-link",
              "state": {
                "file": "docs/zh/dev/advanced-widget.md",
                "linksCollapsed": false,
                "unlinkedCollapsed": true
              }
            }
          },
          {
            "id": "9dcb3d0ccb047226",
            "type": "leaf",
            "state": {
              "type": "tag",
              "state": {
                "sortOrder": "frequency",
                "useHierarchy": true
              }
            }
          },
          {
            "id": "3fdfc0883adbcd12",
            "type": "leaf",
            "state": {
              "type": "outline",
              "state": {
                "file": "docs/zh/dev/advanced-widget.md"
              }
            }
          }
        ]
      }
    ],
    "direction": "horizontal",
    "width": 300,
    "collapsed": true
  },
  "left-ribbon": {
    "hiddenItems": {
      "switcher:打开快速切换": false,
      "graph:查看关系图谱": false,
      "canvas:新建白板": false,
      "daily-notes:打开/创建今天的日记": false,
      "templates:插入模板": false,
      "command-palette:打开命令面板": false
    }
  },
  "active": "343b98d9e91f4cd8",
  "lastOpenFiles": [
    "docs/zh/dev/basic-widget.md",
    "docs/zh/dev/advanced-widget.md",
    "skia.org.md",
    "未命名.md",
    "docs/zh/dev",
    "未命名",
    "docs/zh/api/animations.md",
    "docs/zh/api/basic/arrow.md",
    "docs/zh/api/basic/arc.md",
    "docs/examples/Demo3.vue",
    "node_modules/@newcar",
    "_tmp_28204_9913d128dd4fc0ca94bf9b382c72a8dc",
    "pnpm-lock.yaml.1595350293",
    "_tmp_9920_419365c6e03c8fb386743377845df178",
    "_tmp_24740_10792ec5d504ad85d12491c43d83f74a",
    "_tmp_25944_80590ac745abdd4642df02ef90569dcc",
    "docs/examples/Demo2.vue",
    "docs/examples.md",
    "docs/zh/advanced/preload.md",
    "docs/advanced/preload.md",
    "docs/zh/api/apis/use-font.md",
    "docs/zh/api/apis/index.md",
    "docs/zh/api/apis/define-car-plugin.md",
    "docs/zh/api/apis/define-animation.md",
    "docs/zh/api/apis/change-style.md",
    "docs/zh/api/apis/change-property.md",
    "docs/zh/api/index.md",
    "docs/zh/getting-started.md",
    "docs/advanced/update-function.md",
    "docs/public/Banner.webp",
    "docs/public/uni.webp",
    "docs/zh/advanced/update-function.md",
    "docs/zh/advanced/recorder.md",
    "docs/zh/advanced/parents-children-widget.md",
    "docs/advanced/recorder.md",
    "docs/advanced/color-system.md",
    "docs/zh/advanced/color-system.md",
    "docs/zh/advanced/animation.md"
  ]
}
